Workbook

Sheet 最新追加任务情况
F1: 是否包含核心重点 | G1: 是否之前已登记 | L1: NEW-M1-农林牧渔-生猪价格
A2: 1-行业经济 | B2: 行业经济\交运\日 | C2: NEW-DWMY-交运-中航信-当日预定指数-日-人工 | D2: 日 | E2: =VLOOKUP(C2,任务详情!B:E,4,0) -> 1 | F2: 否 | G2: 是 | H2: 模版频率 | I2: 点击不处理后追加 | L2: NEW-M7-化工-隆众进出口-原盐就出口(月)
A3: 1-行业经济 | B3: 行业经济\交运\日 | C3: NEW-DWMY-交运-中航信-需求指数-人工 | D3: 日 | E3: =VLOOKUP(C3,任务详情!B:E,4,0) -> 1 | F3: 是 | G3: 是 | H3: 日 | I3: 1 | L3: NEW-Q3-金融-行业协会-基金业:资产管理行业数据
A4: 1-行业经济 | B4: 行业经济\化工\半周 | C4: NEW-HW1-化工-库存模板-丙酮江阴库存-人工 | D4: 日 | E4: =VLOOKUP(C4,任务详情!B:E,4,0) -> 1 | F4: 是 | G4: 是 | H4: 不定期 | I4: 1 | L4: 新宏观-Y10-国统局资源和环境-分省-水资源
A5: 1-行业经济 | B5: 行业经济\化工\半周 | C5: NEW-HW1-化工-库存模板-华东主港乙二醇库存及主流库区统计分析-人工 | D5: 日 | E5: =VLOOKUP(C5,任务详情!B:E,4,0) -> 1 | F5: 是 | G5: 是 | H5: 周 | I5: 1 | L5: NEW-W1-煤炭-CCTD秦皇岛动力煤价格
A6: 1-行业经济 | B6: 行业经济\化工\半周 | C6: NEW-HW1-化工-库存模板-华东乙二醇码头库存-人工 | D6: 日 | E6: =VLOOKUP(C6,任务详情!B:E,4,0) -> 1 | F6: 是 | G6: 是 | H6: 旬 | I6: 1 | L6: NEW-D8-化工-化纤
A7: 1-行业经济 | B7: 行业经济\化工\半周 | C7: NEW-HW1-化工-库存模板-苯酚江阴港口库存-人工 | D7: 日 | E7: =VLOOKUP(C7,任务详情!B:E,4,0) -> 1 | F7: 否 | G7: 是 | H7: 月 | I7: 3 | L7: 新宏观-Y1-国统局-最新发布-国民经济
A8: 1-行业经济 | B8: 行业经济\TMT\日 | C8: NEW-D1-TMT-每日票房-人工 | D8: 日 | E8: =VLOOKUP(C8,任务详情!B:E,4,0) -> 1 | F8: 否 | G8: 是 | H8: 季 | I8: 3 | L8: 新宏观-M1-wind-中国一致性预期-贸易顺差-1
A9: 1-行业经济 | B9: 行业经济\TMT\日 | C9: NEW-D1-TMT-每日票房-自动化 | D9: 日 | E9: =VLOOKUP(C9,任务详情!B:E,4,0) -> 1 | F9: 否 | G9: 是 | H9: 半年 | I9: 3 | L9: NEW-Y1-金融-证券基金业-私募基金行业
A10: 1-行业经济 | B10: 行业经济\交运\日 | C10: NEW-D1-交运-BDI-人工 | D10: 日 | E10: =VLOOKUP(C10,任务详情!B:E,4,0) -> 1 | F10: 是 | G10: 是 | H10: 年 | I10: 10 | L10: 新宏观-M1-证监会-2
A11: 1-行业经济 | B11: 行业经济\交运\日 | C11: NEW-D1-交运-FDI-人工 | D11: 日 | E11: =VLOOKUP(C11,任务详情!B:E,4,0) -> 1 | F11: 是 | G11: 是 | L11: NEW-M2-医药-中药材指数
A12: 1-行业经济 | B12: 行业经济\交运\日 | C12: NEW-D1-交运-中国水运网运价-人工 | D12: 日 | E12: =VLOOKUP(C12,任务详情!B:E,4,0) -> 1 | F12: 否 | G12: 是 | L12: 新宏观-M1-山东省统计局-公共数据
A13: 1-行业经济 | B13: 行业经济\交运\日 | C13: NEW-D1-交运-中国进口原油运价-人工 | D13: 日 | E13: =VLOOKUP(C13,任务详情!B:E,4,0) -> 1 | F13: 是 | G13: 是 | L13: 【经营数据】-食品饮料-HY1-颐海国际
A14: 1-行业经济 | B14: 行业经济\交运\日 | C14: NEW-D1-交运-全球集装箱-自动化 | D14: 日 | E14: =VLOOKUP(C14,任务详情!B:E,4,0) -> 1 | F14: 否 | G14: 是 | L14: 地方经济运行-M1-云南(非重点)-丽江市-宁蒗彝族自治县
A15: 1-行业经济 | B15: 行业经济\交运\日 | C15: NEW-D1-交运-周涨跌幅衍生计算-人工 | D15: 日 | E15: =VLOOKUP(C15,任务详情!B:E,4,0) -> 1 | F15: 是 | G15: 是 | L15: 地方经济四期-Y1-浙江省统计年鉴-绍兴市统计局
A16: 1-行业经济 | B16: 行业经济\交运\日 | C16: NEW-D1-交运-股指-人工 | D16: 日 | E16: =VLOOKUP(C16,任务详情!B:E,4,0) -> 1 | F16: 是 | G16: 是 | L16: 国际宏观-Y1-欧洲-央行-债务
A17: 1-行业经济 | B17: 行业经济\交运\日 | C17: NEW-D1-交运-股指-自动化 | D17: 日 | E17: =VLOOKUP(C17,任务详情!B:E,4,0) -> 1 | F17: 否 | G17: 是 | L17: 地方经济运行-M1-云南(非重点)-楚雄州-南华县
A18: 1-行业经济 | B18: 行业经济\交运\日 | C18: NEW-D1-交运-运力-CDI-人工 | D18: 日 | E18: =VLOOKUP(C18,任务详情!B:E,4,0) -> 1 | F18: 否 | G18: 是 | L18: NEW-M2-房地产-70大城市房价指数-房价租金比
A19: 1-行业经济 | B19: 行业经济\交运\日 | C19: NEW-D1-交运-运力-分公司-人工 | D19: 日 | E19: =VLOOKUP(C19,任务详情!B:E,4,0) -> 1 | F19: 是 | G19: 是 | L19: NEW-W1-机械设备-庞源指数
A20: 1-行业经济 | B20: 行业经济\交运\日 | C20: NEW-D1-交运-进口干散货运价-人工 | D20: 日 | E20: =VLOOKUP(C20,任务详情!B:E,4,0) -> 1 | F20: 是 | G20: 是 | L20: 地方经济三期-Y35-云南省统计公报-文山州
A21: 1-行业经济 | B21: 行业经济\交运\日 | C21: NEW-D1-交运-远东干散货-自动化 | D21: 日 | E21: =VLOOKUP(C21,任务详情!B:E,4,0) -> 1 | F21: 否 | G21: 是 | L21: 新宏观-Y1-央行-中国区域金融运行报告
A22: 1-行业经济 | B22: 行业经济\交运\日 | C22: NEW-D1-交运-集装箱期租-自动化 | D22: 日 | E22: =VLOOKUP(C22,任务详情!B:E,4,0) -> 1 | F22: 否 | G22: 是 | L22: NEW-D6-钢铁-冶金焦价格
... A1691: 1-行业经济 | B1691: 行业经济\食品饮料\日 | C1691: NEW-D1-食品饮料-鹌鹑蛋-人工 | D1691: 日 | E1691: =VLOOKUP(C1691,任务详情!B:E,4,0) -> 1 | F1691: 否 | G1691: 是 | L1691: 【经营数据】-休闲服务-首旅酒店QHY-首旅酒店-年
A1692: 2-中国宏观 | B1692: #VALUE! | C1692: 新宏观-D1-上海证券交易所-债券成交概况-人工 | D1692: 日 | E1692: =VLOOKUP(C1692,任务详情!B:E,4,0) -> 1 | F1692: 否 | G1692: 是 | L1692: 国际宏观-M1-美国-商务部-制造商的商品
A1693: 2-中国宏观 | B1693: 中国宏观\中国人民银行\日 | C1693: 新宏观-D1-央行货币政策-CBS-自动化 | D1693: 日 | E1693: =VLOOKUP(C1693,任务详情!B:E,4,0) -> 1 | F1693: 否 | G1693: 是 | L1693: NEW-D2-房地产(T)-连云港商品房
A1694: 2-中国宏观 | B1694: 中国宏观\中国人民银行\日 | C1694: 新宏观-D1-央行货币政策-SLO-人工 | D1694: 日 | E1694: =VLOOKUP(C1694,任务详情!B:E,4,0) -> 1 | F1694: 否 | G1694: 是 | L1694: NEW-Y1-钢铁-(人均)表观消费量-W
A1695: 2-中国宏观 | B1695: 中国宏观\中国人民银行\日 | C1695: 新宏观-D1-央行货币政策-再贷款、再贴现利率表-人工 | D1695: 日 | E1695: =VLOOKUP(C1695,任务详情!B:E,4,0) -> 1 | F1695: 否 | G1695: 是 | L1695: NEW-D2-化工-隆众化工-C5C9共聚石油树脂国内市场价
A1696: 2-中国宏观 | B1696: 中国宏观\中国人民银行\日 | C1696: 新宏观-D1-央行货币政策-回购-人工 | D1696: 日 | E1696: =VLOOKUP(C1696,任务详情!B:E,4,0) -> 1 | F1696: 否 | G1696: 是 | L1696: NEW-M1-化工-OPEC-液化气产量
A1697: 2-中国宏观 | B1697: 中国宏观\中国人民银行\日 | C1697: 新宏观-D1-央行货币政策-国库现金管理-人工 | D1697: 日 | E1697: =VLOOKUP(C1697,任务详情!B:E,4,0) -> 1 | F1697: 否 | G1697: 是 | L1697: NEW-M8-房地产-资阳市商品房交易走势
A1698: 2-中国宏观 | B1698: 中国宏观\中国人民银行\日 | C1698: 新宏观-D1-央行货币政策-特别国债-人工 | D1698: 日 | E1698: =VLOOKUP(C1698,任务详情!B:E,4,0) -> 1 | F1698: 否 | G1698: 是 | L1698: NEW-W1-化工-隆众网页-周四-18
A1699: 2-中国宏观 | B1699: 中国宏观\中国外汇交易中心\日 | C1699: 【核心&重点指标】-新宏观-Wind替代数据源-中国外汇交易中心-利率日-自动化 | D1699: 日 | E1699: =VLOOKUP(C1699,任务详情!B:E,4,0) -> 1 | F1699: 否 | G1699: 是 | L1699: NEW-M14-交运-港口数据-新加坡港
A1700: 2-中国宏观 | B1700: 中国宏观\中国外汇交易中心\日 | C1700: 新宏观-D1-中国外汇交易中心-RMBS条件早偿率指数-人工 | D1700: 日 | E1700: =VLOOKUP(C1700,任务详情!B:E,4,0) -> 1 | F1700: 否 | G1700: 是 | L1700: NEW-D2-化工-隆众化工-丙烯酸乙酯国内市场价
A1701: 2-中国宏观 | B1701: 中国宏观\中国外汇交易中心\日 | C1701: 新宏观-D1-中国外汇交易中心-买断式回购日报-自动化 | D1701: 日 | E1701: =VLOOKUP(C1701,任务详情!B:E,4,0) -> 1 | F1701: 否 | G1701: 是 | L1701: NEW-Q1-计算机(需百度)-服务器数据
A1702: 2-中国宏观 | B1702: 中国宏观\中国外汇交易中心\日 | C1702: 新宏观-D1-中国外汇交易中心-利率-自动化 | D1702: 日 | E1702: =VLOOKUP(C1702,任务详情!B:E,4,0) -> 1 | F1702: 否 | G1702: 是 | L1702: NEW-D2-房地产(T)-嘉兴商品房
A1703: 2-中国宏观 | B1703: 中国宏观\中国外汇交易中心\日 | C1703: 新宏观-D1-中国外汇交易中心-利率互换日报-自动化 | D1703: 日 | E1703: =VLOOKUP(C1703,任务详情!B:E,4,0) -> 1 | F1703: 否 | G1703: 是 | L1703: 地方经济运行-M1-云南(非重点)-文山州
A1704: 2-中国宏观 | B1704: 中国宏观\中国外汇交易中心\日 | C1704: 新宏观-D1-中国外汇交易中心-利率互换曲线-自动化 | D1704: 日 | E1704: =VLOOKUP(C1704,任务详情!B:E,4,0) -> 1 | F1704: 否 | G1704: 是 | L1704: NEW-M10-金融市场-期货市场交易情况
... A5497: 4-地方经济 | B5497: 地方经济\月、季频模板\各省、市、区县模板\新疆维吾尔自治区 | C5497: 地方经济运行-M1-新疆(非重点)-巴音郭楞州区县-人工 | D5497: 月 | E5497: =VLOOKUP(C5497,任务详情!B:E,4,0) -> 3 | F5497: 否 | G5497: 是 | L5497: 地方经济运行-M1-云南(非重点)-德宏州-芒市
A5498: 4-地方经济 | B5498: 地方经济\月、季频模板\各省、市、区县模板\新疆维吾尔自治区 | C5498: 地方经济运行-M1-新疆(非重点)-新疆-人工 | D5498: 月 | E5498: =VLOOKUP(C5498,任务详情!B:E,4,0) -> 1 | F5498: 是 | G5498: 是
A5499: 4-地方经济 | B5499: 地方经济\月、季频模板\各省、市、区县模板\新疆维吾尔自治区 | C5499: 地方经济运行-M1-新疆(非重点)-昌吉回族-人工 | D5499: 月 | E5499: =VLOOKUP(C5499,任务详情!B:E,4,0) -> 3 | F5499: 否 | G5499: 是
A5500: 4-地方经济 | B5500: 地方经济\月、季频模板\各省、市、区县模板\新疆维吾尔自治区 | C5500: 地方经济运行-M1-新疆(非重点)-昌吉回族区县-人工 | D5500: 月 | E5500: =VLOOKUP(C5500,任务详情!B:E,4,0) -> 3 | F5500: 否 | G5500: 是
A5501: 4-地方经济 | B5501: 地方经济\月、季频模板\各省、市、区县模板\新疆维吾尔自治区 | C5501: 地方经济运行-M1-新疆(非重点)-石河子-人工 | D5501: 月 | E5501: =VLOOKUP(C5501,任务详情!B:E,4,0) -> 3 | F5501: 否 | G5501: 是
A5502: 4-地方经济 | B5502: 地方经济\月、季频模板\各省、市、区县模板\新疆维吾尔自治区 | C5502: 地方经济运行-M1-新疆(非重点)-阿克苏-人工 | D5502: 月 | E5502: =VLOOKUP(C5502,任务详情!B:E,4,0) -> 3 | F5502: 否 | G5502: 是
A5503: 4-地方经济 | B5503: 地方经济\月、季频模板\各省、市、区县模板\新疆维吾尔自治区 | C5503: 地方经济运行-M1-新疆(非重点)-阿克苏区县-人工 | D5503: 月 | E5503: =VLOOKUP(C5503,任务详情!B:E,4,0) -> 3 | F5503: 否 | G5503: 是
A5504: 4-地方经济 | B5504: 地方经济\月、季频模板\各省、市、区县模板\新疆维吾尔自治区 | C5504: 地方经济运行-M1-新疆(非重点)-阿勒泰区县-人工 | D5504: 月 | E5504: =VLOOKUP(C5504,任务详情!B:E,4,0) -> 3 | F5504: 否 | G5504: 是
A5505: 4-地方经济 | B5505: 地方经济\月、季频模板\各省、市、区县模板\新疆维吾尔自治区 | C5505: 地方经济运行-M1-新疆(非重点)-阿拉尔市-人工 | D5505: 月 | E5505: =VLOOKUP(C5505,任务详情!B:E,4,0) -> 3 | F5505: 否 | G5505: 是
A5506: 4-地方经济 | B5506: 地方经济\月、季频模板\各省、市、区县模板\无锡市 | C5506: 地方经济运行-M1-无锡市-宜兴市-人工 | D5506: 月 | E5506: =VLOOKUP(C5506,任务详情!B:E,4,0) -> 3 | F5506: 否 | G5506: 是
A5507: 4-地方经济 | B5507: 地方经济\月、季频模板\各省、市、区县模板\无锡市 | C5507: 地方经济运行-M1-无锡市-惠山区-自动化 | D5507: 月 | E5507: =VLOOKUP(C5507,任务详情!B:E,4,0) -> 3 | F5507: 否 | G5507: 是
A5508: 4-地方经济 | B5508: 地方经济\月、季频模板\各省、市、区县模板\无锡市 | C5508: 地方经济运行-M1-无锡市-无锡-人工 | D5508: 月 | E5508: =VLOOKUP(C5508,任务详情!B:E,4,0) -> 1 | F5508: 是 | G5508: 是
A5509: 4-地方经济 | B5509: 地方经济\月、季频模板\各省、市、区县模板\无锡市 | C5509: 地方经济运行-M1-无锡市-无锡市专利交通邮政-人工 | D5509: 月 | E5509: =VLOOKUP(C5509,任务详情!B:E,4,0) -> 3 | F5509: 否 | G5509: 是
... A8466: 4-地方经济 | B8466: 地方经济\年频模板\财政模板\黑龙江省 | C8466: 地方经济三期-Y40-黑龙江财政-齐齐哈尔市-人工 | D8466: 年 | E8466: =VLOOKUP(C8466,任务详情!B:E,4,0) -> 10 | F8466: 否 | G8466: 是
A8467: 1-行业经济 | B8467: 行业经济\农林牧渔\日 | C8467: NEW-D7-农林牧渔-土豆-自动化 | D8467: 日 | E8467: =VLOOKUP(D8467,H:I,2,0) -> 1 | F8467: 否 | G8467: 否
A8468: 4-地方经济 | B8468: 地方经济\年频模板\区县预决算\河北省 | C8468: 地方经济四期_河北省各区县预决算报告-保定-涞水县-人工 | D8468: 年 | E8468: =VLOOKUP(D8468,H:I,2,0) -> 10 | F8468: 否 | G8468: 否
A8469: 2-中国宏观 | B8469: 中国宏观\财政\年 | C8469: 【核心&重点指标】-新宏观-Wind替代数据源-财政部-年-10条指标-2-财政-年-宏观-人工 | D8469: 年 | E8469: =VLOOKUP(D8469,H:I,2,0) -> 10 | F8469: 否 | G8469: 否
A8470: 2-中国宏观 | B8470: 中国宏观\国家统计局\国统局-全国\年 | C8470: 【核心&重点指标】-新宏观-Wind替代数据源-国家统计局-年-182个指标-对外经济贸易-宏观-人工 | D8470: 年 | E8470: =VLOOKUP(D8470,H:I,2,0) -> 10 | F8470: 否 | G8470: 否
A8471: 2-中国宏观 | B8471: 中国宏观\国家统计局\国统局-全国\年 | C8471: 【核心&重点指标】-新宏观-Wind替代数据源-国家统计局-年-182个指标-分省GDP-宏观-人工 | D8471: 年 | E8471: =VLOOKUP(D8471,H:I,2,0) -> 10 | F8471: 否 | G8471: 否
A8472: 2-中国宏观 | B8472: 中国宏观\国家统计局\国统局-全国\年 | C8472: 【核心&重点指标】-新宏观-Wind替代数据源-国家统计局-年-182个指标-分省建筑业-宏观-自动化 | D8472: 年 | E8472: =VLOOKUP(D8472,H:I,2,0) -> 10 | F8472: 否 | G8472: 否
A8473: 2-中国宏观 | B8473: 中国宏观\国家统计局\国统局-全国\年 | C8473: 【核心&重点指标】-新宏观-Wind替代数据源-国家统计局-年-182个指标-工业-宏观-自动化 | D8473: 年 | E8473: =VLOOKUP(D8473,H:I,2,0) -> 10 | F8473: 否 | G8473: 否
A8474: 2-中国宏观 | B8474: 中国宏观\国家统计局\国统局-全国\年 | C8474: 【核心&重点指标】-新宏观-Wind替代数据源-国家统计局-年-182个指标-固定资产和房地产-宏观-人工 | D8474: 年 | E8474: =VLOOKUP(D8474,H:I,2,0) -> 10 | F8474: 否 | G8474: 否
A8475: 2-中国宏观 | B8475: 中国宏观\国家统计局\国统局-全国\年 | C8475: 【核心&重点指标】-新宏观-Wind替代数据源-国家统计局-年-182个指标-国民经济核算-宏观-自动化 | D8475: 年 | E8475: =VLOOKUP(D8475,H:I,2,0) -> 10 | F8475: 否 | G8475: 否
A8476: 2-中国宏观 | B8476: 中国宏观\国家统计局\国统局-全国\年 | C8476: 【核心&重点指标】-新宏观-Wind替代数据源-国家统计局-年-182个指标-建筑业-宏观-人工 | D8476: 年 | E8476: =VLOOKUP(D8476,H:I,2,0) -> 10 | F8476: 否 | G8476: 否
A8477: 2-中国宏观 | B8477: 中国宏观\国家统计局\国统局-全国\年 | C8477: 【核心&重点指标】-新宏观-Wind替代数据源-国家统计局-年-182个指标-金融业-宏观-人工 | D8477: 年 | E8477: =VLOOKUP(D8477,H:I,2,0) -> 10 | F8477: 否 | G8477: 否
A8478: 2-中国宏观 | B8478: 中国宏观\国家统计局\国统局-全国\年 | C8478: 【核心&重点指标】-新宏观-Wind替代数据源-国家统计局-年-182个指标-就业人员与工资-宏观-人工 | D8478: 年 | E8478: =VLOOKUP(D8478,H:I,2,0) -> 10 | F8478: 否 | G8478: 否
... A8495: 1-行业经济 | B8495: 行业经济\化工\日 | C8495: NEW-D1-化工-隆众化工能源-D系列溶剂油出厂价-自动化 | D8495: 日 | E8495: =VLOOKUP(D8495,H:I,2,0) -> 1 | F8495: 否 | G8495: 否
A8496: 1-行业经济 | B8496: 行业经济\化工\日 | C8496: NEW-D1-化工-隆众化工能源-MTBE出厂价-人工 | D8496: 日 | E8496: 1 | F8496: 是 | G8496: 是
A8497: 1-行业经济 | B8497: 行业经济\化工\日 | C8497: NEW-D1-化工-隆众化工能源-MTBE出厂价-自动化 | D8497: 日 | E8497: =VLOOKUP(D8497,H:I,2,0) -> 1 | F8497: 否 | G8497: 否
A8498: 1-行业经济 | B8498: 行业经济\化工\日 | C8498: NEW-D1-化工-隆众化工能源-MTBE国际市场价-自动化 | D8498: 日 | E8498: =VLOOKUP(D8498,H:I,2,0) -> 1 | F8498: 否 | G8498: 否
A8499: 1-行业经济 | B8499: 行业经济\化工\日 | C8499: NEW-D1-化工-隆众化工能源-MTBE市场价-自动化 | D8499: 日 | E8499: =VLOOKUP(D8499,H:I,2,0) -> 1 | F8499: 否 | G8499: 否
A8500: 1-行业经济 | B8500: 行业经济\化工\日 | C8500: NEW-D1-化工-隆众化工能源-白油出厂价-人工 | D8500: 日 | E8500: =VLOOKUP(D8500,H:I,2,0) -> 1 | F8500: 否 | G8500: 否
A8501: 1-行业经济 | B8501: 行业经济\化工\日 | C8501: NEW-D1-化工-隆众化工能源-白油出厂价-自动化 | D8501: 日 | E8501: =VLOOKUP(D8501,H:I,2,0) -> 1 | F8501: 否 | G8501: 否
A8502: 1-行业经济 | B8502: 行业经济\化工\日 | C8502: NEW-D1-化工-隆众化工能源-丙烷出厂价-人工 | D8502: 日 | E8502: 1 | F8502: 是 | G8502: 是
A8503: 1-行业经济 | B8503: 行业经济\化工\日 | C8503: NEW-D1-化工-隆众化工能源-丙烷出厂价-自动化 | D8503: 日 | E8503: =VLOOKUP(D8503,H:I,2,0) -> 1 | F8503: 否 | G8503: 否
A8504: 1-行业经济 | B8504: 行业经济\化工\日 | C8504: NEW-D1-化工-隆众化工能源-丙烷国际市场价-自动化 | D8504: 日 | E8504: =VLOOKUP(D8504,H:I,2,0) -> 1 | F8504: 否 | G8504: 否
A8505: 1-行业经济 | B8505: 行业经济\化工\日 | C8505: NEW-D1-化工-隆众化工能源-柴油出厂价-人工 | D8505: 日 | E8505: 1 | F8505: 是 | G8505: 是
A8506: 1-行业经济 | B8506: 行业经济\化工\日 | C8506: NEW-D1-化工-隆众化工能源-柴油出厂价-自动化 | D8506: 日 | E8506: =VLOOKUP(D8506,H:I,2,0) -> 1 | F8506: 否 | G8506: 否
A8507: 1-行业经济 | B8507: 行业经济\化工\日 | C8507: NEW-D1-化工-隆众化工能源-柴油国际市场价-人工 | D8507: 日 | E8507: 1 | F8507: 是 | G8507: 是
A8508: 1-行业经济 | B8508: 行业经济\化工\日 | C8508: NEW-D1-化工-隆众化工能源-柴油国际市场价-自动化 | D8508: 日 | E8508: =VLOOKUP(D8508,H:I,2,0) -> 1 | F8508: 否 | G8508: 否
A8509: 1-行业经济 | B8509: 行业经济\化工\日 | C8509: NEW-D1-化工-隆众化工能源-柴油零售限价-人工 | D8509: 日 | E8509: =VLOOKUP(D8509,H:I,2,0) -> 1 | F8509: 否 | G8509: 否
A8510: 1-行业经济 | B8510: 行业经济\化工\日 | C8510: NEW-D1-化工-隆众化工能源-柴油批发价-人工 | D8510: 日 | E8510: =VLOOKUP(D8510,H:I,2,0) -> 1 | F8510: 否 | G8510: 否
A8511: 1-行业经济 | B8511: 行业经济\化工\日 | C8511: NEW-D1-化工-隆众化工能源-柴油批发价-自动化 | D8511: 日 | E8511: =VLOOKUP(D8511,H:I,2,0) -> 1 | F8511: 否 | G8511: 否
A8512: 1-行业经济 | B8512: 行业经济\化工\日 | C8512: NEW-D1-化工-隆众化工能源-柴油市场价-人工 | D8512: 日 | E8512: =VLOOKUP(D8512,H:I,2,0) -> 1 | F8512: 否 | G8512: 否
A8513: 1-行业经济 | B8513: 行业经济\化工\日 | C8513: NEW-D1-化工-隆众化工能源-柴油市场价-自动化 | D8513: 日 | E8513: =VLOOKUP(D8513,H:I,2,0) -> 1 | F8513: 否 | G8513: 否
A8514: 1-行业经济 | B8514: 行业经济\化工\日 | C8514: NEW-D1-化工-隆众化工能源-丁烷出厂价-人工 | D8514: 日 | E8514: =VLOOKUP(D8514,H:I,2,0) -> 1 | F8514: 否 | G8514: 否
A8515: 1-行业经济 | B8515: 行业经济\化工\日 | C8515: NEW-D1-化工-隆众化工能源-丁烷出厂价-自动化 | D8515: 日 | E8515: =VLOOKUP(D8515,H:I,2,0) -> 1 | F8515: 否 | G8515: 否
A8516: 1-行业经济 | B8516: 行业经济\化工\日 | C8516: NEW-D1-化工-隆众化工能源-丁烷国际市场价-自动化 | D8516: 日 | E8516: =VLOOKUP(D8516,H:I,2,0) -> 1 | F8516: 否 | G8516: 否
A8517: 1-行业经济 | B8517: 行业经济\化工\日 | C8517: NEW-D1-化工-隆众化工能源-煅烧焦出厂价-人工 | D8517: 日 | E8517: =VLOOKUP(D8517,H:I,2,0) -> 1 | F8517: 否 | G8517: 否
A8518: 1-行业经济 | B8518: 行业经济\化工\日 | C8518: NEW-D1-化工-隆众化工能源-煅烧焦出厂价-自动化 | D8518: 日 | E8518: =VLOOKUP(D8518,H:I,2,0) -> 1 | F8518: 否 | G8518: 否
A8519: 1-行业经济 | B8519: 行业经济\化工\日 | C8519: NEW-D1-化工-隆众化工能源-二甲醚出厂价-人工 | D8519: 日 | E8519: 1 | F8519: 是 | G8519: 是
A8520: 1-行业经济 | B8520: 行业经济\化工\日 | C8520: NEW-D1-化工-隆众化工能源-二甲醚出厂价-自动化 | D8520: 日 | E8520: =VLOOKUP(D8520,H:I,2,0) -> 1 | F8520: 否 | G8520: 否
A8521: 1-行业经济 | B8521: 行业经济\化工\日 | C8521: NEW-D1-化工-隆众化工能源-二甲醚市场价-人工 | D8521: 日 | E8521: =VLOOKUP(D8521,H:I,2,0) -> 1 | F8521: 否 | G8521: 否
A8522: 1-行业经济 | B8522: 行业经济\化工\日 | C8522: NEW-D1-化工-隆众化工能源-二甲醚市场价-自动化 | D8522: 日 | E8522: =VLOOKUP(D8522,H:I,2,0) -> 1 | F8522: 否 | G8522: 否
A8523: 1-行业经济 | B8523: 行业经济\化工\日 | C8523: NEW-D1-化工-隆众化工能源-芳烃溶剂油出厂价-人工 | D8523: 日 | E8523: =VLOOKUP(D8523,H:I,2,0) -> 1 | F8523: 否 | G8523: 否
A8524: 1-行业经济 | B8524: 行业经济\化工\日 | C8524: NEW-D1-化工-隆众化工能源-芳烃溶剂油出厂价-自动化 | D8524: 日 | E8524: =VLOOKUP(D8524,H:I,2,0) -> 1 | F8524: 否 | G8524: 否
A8525: 1-行业经济 | B8525: 行业经济\化工\日 | C8525: NEW-D1-化工-隆众化工能源-芳烃溶剂油市场价-人工 | D8525: 日 | E8525: =VLOOKUP(D8525,H:I,2,0) -> 1 | F8525: 否 | G8525: 否
A8526: 1-行业经济 | B8526: 行业经济\化工\日 | C8526: NEW-D1-化工-隆众化工能源-芳烃溶剂油市场价-自动化 | D8526: 日 | E8526: =VLOOKUP(D8526,H:I,2,0) -> 1 | F8526: 否 | G8526: 否
A8527: 1-行业经济 | B8527: 行业经济\化工\日 | C8527: NEW-D1-化工-隆众化工能源-工业用碳十粗芳烃出厂价-人工 | D8527: 日 | E8527: =VLOOKUP(D8527,H:I,2,0) -> 1 | F8527: 否 | G8527: 否
A8528: 1-行业经济 | B8528: 行业经济\化工\日 | C8528: NEW-D1-化工-隆众化工能源-工业用碳十粗芳烃出厂价-自动化 | D8528: 日 | E8528: =VLOOKUP(D8528,H:I,2,0) -> 1 | F8528: 否 | G8528: 否
A8529: 1-行业经济 | B8529: 行业经济\化工\日 | C8529: NEW-D1-化工-隆众化工能源-工业用碳十粗芳烃市场价-人工 | D8529: 日 | E8529: =VLOOKUP(D8529,H:I,2,0) -> 1 | F8529: 否 | G8529: 否
A8530: 1-行业经济 | B8530: 行业经济\化工\日 | C8530: NEW-D1-化工-隆众化工能源-工业用碳十粗芳烃市场价-自动化 | D8530: 日 | E8530: =VLOOKUP(D8530,H:I,2,0) -> 1 | F8530: 否 | G8530: 否
A8531: 1-行业经济 | B8531: 行业经济\化工\日 | C8531: NEW-D1-化工-隆众化工能源-混合芳烃出厂价-人工 | D8531: 日 | E8531: =VLOOKUP(D8531,H:I,2,0) -> 1 | F8531: 否 | G8531: 否
A8532: 1-行业经济 | B8532: 行业经济\化工\日 | C8532: NEW-D1-化工-隆众化工能源-混合芳烃出厂价-自动化 | D8532: 日 | E8532: =VLOOKUP(D8532,H:I,2,0) -> 1 | F8532: 否 | G8532: 否
...

Sheet 任务详情
A1: 判断逻辑： | B1: 如果有核心重点指标，默认一天后会再次生成任务。其余按照H:I列时效性追加
A2: 所属模块 | B2: 模版名称 | C2: 模版频率 | D2: 是否核心重点 | E2: 点击不处理后追加调度 | F2: NEW-DWMY-交运-中航信-当日预定指数-日-人工 | G2: =VLOOKUP(F2,B:E,4,0) -> 1 | H2: 模版频率 | I2: 点击不处理后追加
A3: 1-行业经济 | B3: NEW-DWMY-交运-中航信-当日预定指数-日-人工 | C3: 日 | D3: 否 | E3: =VLOOKUP(C3,H:I,2,0) -> 1 | F3: NEW-DWMY-交运-中航信-需求指数-人工 | G3: =VLOOKUP(F3,B:E,4,0) -> 1 | H3: 日 | I3: 1
A4: 1-行业经济 | B4: NEW-DWMY-交运-中航信-需求指数-人工 | C4: 日 | D4: 是 | E4: 1 | F4: NEW-HW1-化工-库存模板-丙酮江阴库存-人工 | G4: =VLOOKUP(F4,B:E,4,0) -> 1 | H4: 不定期 | I4: 1
A5: 1-行业经济 | B5: NEW-HW1-化工-库存模板-丙酮江阴库存-人工 | C5: 日 | D5: 是 | E5: 1 | F5: NEW-HW1-化工-库存模板-华东主港乙二醇库存及主流库区统计分析-人工 | G5: =VLOOKUP(F5,B:E,4,0) -> 1 | H5: 周 | I5: 1
A6: 1-行业经济 | B6: NEW-HW1-化工-库存模板-华东主港乙二醇库存及主流库区统计分析-人工 | C6: 日 | D6: 是 | E6: 1 | F6: NEW-HW1-化工-库存模板-华东乙二醇码头库存-人工 | G6: =VLOOKUP(F6,B:E,4,0) -> 1 | H6: 旬 | I6: 1
A7: 1-行业经济 | B7: NEW-HW1-化工-库存模板-华东乙二醇码头库存-人工 | C7: 日 | D7: 是 | E7: 1 | F7: NEW-HW1-化工-库存模板-苯酚江阴港口库存-人工 | G7: =VLOOKUP(F7,B:E,4,0) -> 1 | H7: 月 | I7: 3
A8: 1-行业经济 | B8: NEW-HW1-化工-库存模板-苯酚江阴港口库存-人工 | C8: 日 | D8: 否 | E8: =VLOOKUP(C8,H:I,2,0) -> 1 | F8: NEW-D1-TMT-每日票房-人工 | G8: =VLOOKUP(F8,B:E,4,0) -> 1 | H8: 季 | I8: 3
A9: 1-行业经济 | B9: NEW-D1-TMT-每日票房-人工 | C9: 日 | D9: 否 | E9: =VLOOKUP(C9,H:I,2,0) -> 1 | F9: NEW-D1-TMT-每日票房-自动化 | G9: =VLOOKUP(F9,B:E,4,0) -> 1 | H9: 半年 | I9: 3
A10: 1-行业经济 | B10: NEW-D1-TMT-每日票房-自动化 | C10: 日 | D10: 否 | E10: =VLOOKUP(C10,H:I,2,0) -> 1 | F10: NEW-D1-交运-BDI-人工 | G10: =VLOOKUP(F10,B:E,4,0) -> 1 | H10: 年 | I10: 10
A11: 1-行业经济 | B11: NEW-D1-交运-BDI-人工 | C11: 日 | D11: 是 | E11: 1 | F11: NEW-D1-交运-FDI-人工 | G11: =VLOOKUP(F11,B:E,4,0) -> 1
A12: 1-行业经济 | B12: NEW-D1-交运-FDI-人工 | C12: 日 | D12: 是 | E12: 1 | F12: NEW-D1-交运-中国水运网运价-人工 | G12: =VLOOKUP(F12,B:E,4,0) -> 1
A13: 1-行业经济 | B13: NEW-D1-交运-中国水运网运价-人工 | C13: 日 | D13: 否 | E13: =VLOOKUP(C13,H:I,2,0) -> 1 | F13: NEW-D1-交运-中国进口原油运价-人工 | G13: =VLOOKUP(F13,B:E,4,0) -> 1
A14: 1-行业经济 | B14: NEW-D1-交运-中国进口原油运价-人工 | C14: 日 | D14: 是 | E14: 1 | F14: NEW-D1-交运-全球集装箱-自动化 | G14: =VLOOKUP(F14,B:E,4,0) -> 1
A15: 1-行业经济 | B15: NEW-D1-交运-全球集装箱-自动化 | C15: 日 | D15: 是 | E15: 1 | F15: NEW-D1-交运-周涨跌幅衍生计算-人工 | G15: =VLOOKUP(F15,B:E,4,0) -> 1
A16: 1-行业经济 | B16: NEW-D1-交运-周涨跌幅衍生计算-人工 | C16: 日 | D16: 是 | E16: 1 | F16: NEW-D1-交运-股指-人工 | G16: =VLOOKUP(F16,B:E,4,0) -> 1
A17: 1-行业经济 | B17: NEW-D1-交运-股指-人工 | C17: 日 | D17: 是 | E17: 1 | F17: NEW-D1-交运-股指-自动化 | G17: =VLOOKUP(F17,B:E,4,0) -> 1
A18: 1-行业经济 | B18: NEW-D1-交运-股指-自动化 | C18: 日 | D18: 是 | E18: 1 | F18: NEW-D1-交运-运力-CDI-人工 | G18: =VLOOKUP(F18,B:E,4,0) -> 1
A19: 1-行业经济 | B19: NEW-D1-交运-运力-CDI-人工 | C19: 日 | D19: 否 | E19: =VLOOKUP(C19,H:I,2,0) -> 1 | F19: NEW-D1-交运-运力-分公司-人工 | G19: =VLOOKUP(F19,B:E,4,0) -> 1
A20: 1-行业经济 | B20: NEW-D1-交运-运力-分公司-人工 | C20: 日 | D20: 是 | E20: 1 | F20: NEW-D1-交运-进口干散货运价-人工 | G20: =VLOOKUP(F20,B:E,4,0) -> 1
A21: 1-行业经济 | B21: NEW-D1-交运-进口干散货运价-人工 | C21: 日 | D21: 是 | E21: 1 | F21: NEW-D1-交运-远东干散货-自动化 | G21: =VLOOKUP(F21,B:E,4,0) -> 1
A22: 1-行业经济 | B22: NEW-D1-交运-远东干散货-自动化 | C22: 日 | D22: 是 | E22: 1 | F22: NEW-D1-交运-集装箱期租-自动化 | G22: =VLOOKUP(F22,B:E,4,0) -> 1
A23: 1-行业经济 | B23: NEW-D1-交运-集装箱期租-自动化 | C23: 日 | D23: 是 | E23: 1 | F23: NEW-D2-交运-地铁客运量-全国物流-人工 | G23: =VLOOKUP(F23,B:E,4,0) -> 1
A24: 1-行业经济 | B24: NEW-D2-交运-地铁客运量-全国物流-人工 | C24: 日 | D24: 是 | E24: 1 | F24: NEW-D2-交运-地铁客运量-地铁23城客运量-人工 | G24: =VLOOKUP(F24,B:E,4,0) -> 1
A25: 1-行业经济 | B25: NEW-D2-交运-地铁客运量-地铁23城客运量-人工 | C25: 日 | D25: 否 | E25: =VLOOKUP(C25,H:I,2,0) -> 1 | F25: NEW-D2-交运-地铁客运量-地铁客运量-自动化 | G25: =VLOOKUP(F25,B:E,4,0) -> 1
A26: 1-行业经济 | B26: NEW-D2-交运-地铁客运量-地铁客运量-自动化 | C26: 日 | D26: 是 | E26: 1 | F26: NEW-D3-交运-高德交通-城市交通(日)-人工 | G26: =VLOOKUP(F26,B:E,4,0) -> 1
A27: 1-行业经济 | B27: NEW-D3-交运-高德交通-城市交通(日)-人工 | C27: 日 | D27: 是 | E27: 1 | F27: NEW-D3-交运-高德交通-百城拥堵延时指数-人工 | G27: =VLOOKUP(F27,B:E,4,0) -> 1
A28: 1-行业经济 | B28: NEW-D3-交运-高德交通-百城拥堵延时指数-人工 | C28: 日 | D28: 否 | E28: =VLOOKUP(C28,H:I,2,0) -> 1 | F28: NEW-D4-交运-公路货运指数-周-人工 | G28: =VLOOKUP(F28,B:E,4,0) -> 1
A29: 1-行业经济 | B29: NEW-D4-交运-公路货运指数-周-人工 | C29: 日 | D29: 是 | E29: 1 | F29: NEW-D4-交运-公路货运指数-日-人工 | G29: =VLOOKUP(F29,B:E,4,0) -> 1
A30: 1-行业经济 | B30: NEW-D4-交运-公路货运指数-日-人工 | C30: 日 | D30: 是 | E30: 1 | F30: NEW-D4-交运-公路货运指数-月-人工 | G30: =VLOOKUP(F30,B:E,4,0) -> 1
A31: 1-行业经济 | B31: NEW-D4-交运-公路货运指数-月-人工 | C31: 日 | D31: 是 | E31: 1 | F31: NEW-D5-交运-百度地图-迁徙规模指数-迁入-人工 | G31: =VLOOKUP(F31,B:E,4,0) -> 1
A32: 1-行业经济 | B32: NEW-D5-交运-百度地图-迁徙规模指数-迁入-人工 | C32: 日 | D32: 是 | E32: 1 | F32: NEW-D5-交运-百度地图-迁徙规模指数-迁出-人工 | G32: =VLOOKUP(F32,B:E,4,0) -> 1
A33: 1-行业经济 | B33: NEW-D5-交运-百度地图-迁徙规模指数-迁出-人工 | C33: 日 | D33: 是 | E33: 1 | F33: NEW-D6-交运-机场-民航运行简报-自动化 | G33: =VLOOKUP(F33,B:E,4,0) -> 1
A34: 1-行业经济 | B34: NEW-D6-交运-机场-民航运行简报-自动化 | C34: 日 | D34: 是 | E34: 1 | F34: NEW-D6-交运-机场-海口美兰国际机场客流量-人工 | G34: =VLOOKUP(F34,B:E,4,0) -> 1
A35: 1-行业经济 | B35: NEW-D6-交运-机场-海口美兰国际机场客流量-人工 | C35: 日 | D35: 是 | E35: 1 | F35: NEW-D6-交运-机场-美国各州机场运营状态-人工 | G35: =VLOOKUP(F35,B:E,4,0) -> 1
A36: 1-行业经济 | B36: NEW-D6-交运-机场-美国各州机场运营状态-人工 | C36: 日 | D36: 否 | E36: =VLOOKUP(C36,H:I,2,0) -> 1 | F36: NEW-D6-交运-机场-美国机场运营状态-自动化 | G36: =VLOOKUP(F36,B:E,4,0) -> 1
A37: 1-行业经济 | B37: NEW-D6-交运-机场-美国机场运营状态-自动化 | C37: 日 | D37: 否 | E37: =VLOOKUP(C37,H:I,2,0) -> 1 | F37: NEW-D6-交运-机场-航司飞机利用情况-人工 | G37: =VLOOKUP(F37,B:E,4,0) -> 1
A38: 1-行业经济 | B38: NEW-D6-交运-机场-航司飞机利用情况-人工 | C38: 日 | D38: 是 | E38: 1 | F38: NEW-D6-交运-机场-航班执行情况-自动化 | G38: =VLOOKUP(F38,B:E,4,0) -> 1
A39: 1-行业经济 | B39: NEW-D6-交运-机场-航班执行情况-自动化 | C39: 日 | D39: 是 | E39: 1 | F39: NEW-D7-交运-TSA安检-自动化 | G39: =VLOOKUP(F39,B:E,4,0) -> 1
A40: 1-行业经济 | B40: NEW-D7-交运-TSA安检-自动化 | C40: 日 | D40: 是 | E40: 1 | F40: NEW-D7-交运-一链通-人工 | G40: =VLOOKUP(F40,B:E,4,0) -> 1
A41: 1-行业经济 | B41: NEW-D7-交运-一链通-人工 | C41: 日 | D41: 否 | E41: =VLOOKUP(C41,H:I,2,0) -> 1 | F41: NEW-D7-交运-北方国际粮食远期运价-人工 | G41: =VLOOKUP(F41,B:E,4,0) -> 1
A42: 1-行业经济 | B42: NEW-D7-交运-北方国际粮食远期运价-人工 | C42: 日 | D42: 是 | E42: 1 | F42: NEW-D7-交运-国内沿海运价-人工 | G42: =VLOOKUP(F42,B:E,4,0) -> 1
A43: 1-行业经济 | B43: NEW-D7-交运-国内沿海运价-人工 | C43: 日 | D43: 是 | E43: 1 | F43: NEW-D7-交运-天津航运指数-人工 | G43: =VLOOKUP(F43,B:E,4,0) -> 1
A44: 1-行业经济 | B44: NEW-D7-交运-天津航运指数-人工 | C44: 日 | D44: 是 | E44: 1 | F44: NEW-D7-交运-春运旅客数据-人工 | G44: =VLOOKUP(F44,B:E,4,0) -> 1
A45: 1-行业经济 | B45: NEW-D7-交运-春运旅客数据-人工 | C45: 日 | D45: 是 | E45: 1 | F45: NEW-D7-交运-船舶资产价值指数-人工 | G45: =VLOOKUP(F45,B:E,4,0) -> 1
A46: 1-行业经济 | B46: NEW-D7-交运-船舶资产价值指数-人工 | C46: 日 | D46: 否 | E46: =VLOOKUP(C46,H:I,2,0) -> 1 | F46: 衍生指标-NEW-D1-交运-自动化 | G46: =VLOOKUP(F46,B:E,4,0) -> 1
A47: 1-行业经济 | B47: 衍生指标-NEW-D1-交运-自动化 | C47: 日 | D47: 否 | E47: =VLOOKUP(C47,H:I,2,0) -> 1 | F47: NEW-D1-传媒-BoxOffice-人工 | G47: =VLOOKUP(F47,B:E,4,0) -> 1
A48: 1-行业经济 | B48: NEW-D1-传媒-BoxOffice-人工 | C48: 日 | D48: 否 | E48: =VLOOKUP(C48,H:I,2,0) -> 1 | F48: NEW-D1-传媒-同花顺-传媒-人工 | G48: =VLOOKUP(F48,B:E,4,0) -> 1
A49: 1-行业经济 | B49: NEW-D1-传媒-同花顺-传媒-人工 | C49: 日 | D49: 是 | E49: 1 | F49: NEW-D1-传媒-同花顺-传媒-自动化 | G49: =VLOOKUP(F49,B:E,4,0) -> 1
A50: 1-行业经济 | B50: NEW-D1-传媒-同花顺-传媒-自动化 | C50: 日 | D50: 是 | E50: 1 | F50: NEW-D1-传媒-同花顺-传媒2-人工 | G50: =VLOOKUP(F50,B:E,4,0) -> 1
A51: 1-行业经济 | B51: NEW-D1-传媒-同花顺-传媒2-人工 | C51: 日 | D51: 否 | E51: =VLOOKUP(C51,H:I,2,0) -> 1 | F51: NEW-D1-公用事业-指数-CECI曹妃甸指数-人工 | G51: =VLOOKUP(F51,B:E,4,0) -> 1
A52: 1-行业经济 | B52: NEW-D1-公用事业-指数-CECI曹妃甸指数-人工 | C52: 日 | D52: 是 | E52: 1 | F52: NEW-D1-公用事业-指数-CNESA储能指数-自动化 | G52: =VLOOKUP(F52,B:E,4,0) -> 1
A53: 1-行业经济 | B53: NEW-D1-公用事业-指数-CNESA储能指数-自动化 | C53: 日 | D53: 否 | E53: =VLOOKUP(C53,H:I,2,0) -> 1 | F53: NEW-D1-公用事业-指数-广东电力交易中心-人工 | G53: =VLOOKUP(F53,B:E,4,0) -> 1
A54: 1-行业经济 | B54: NEW-D1-公用事业-指数-广东电力交易中心-人工 | C54: 日 | D54: 是 | E54: 1 | F54: NEW-D1-公用事业（环保）-AQI指数-自动化 | G54: =VLOOKUP(F54,B:E,4,0) -> 1
A55: 1-行业经济 | B55: NEW-D1-公用事业（环保）-AQI指数-自动化 | C55: 日 | D55: 否 | E55: =VLOOKUP(C55,H:I,2,0) -> 1 | F55: NEW-D1-公用事业（环保）-重点城市PM2.5,PM10日度数据-自动化 | G55: =VLOOKUP(F55,B:E,4,0) -> 1
A56: 1-行业经济 | B56: NEW-D1-公用事业（环保）-重点城市PM2.5,PM10日度数据-自动化 | C56: 日 | D56: 否 | E56: =VLOOKUP(C56,H:I,2,0) -> 1 | F56: NEW-D2-公用事业-碳排放-上海环境能源交易所-人工 | G56: =VLOOKUP(F56,B:E,4,0) -> 1
A57: 1-行业经济 | B57: NEW-D2-公用事业-碳排放-上海环境能源交易所-人工 | C57: 日 | D57: 是 | E57: 1 | F57: NEW-D2-公用事业-碳排放-全国温室气体自愿减排交易市场-人工 | G57: =VLOOKUP(F57,B:E,4,0) -> 1
A58: 1-行业经济 | B58: NEW-D2-公用事业-碳排放-全国温室气体自愿减排交易市场-人工 | C58: 日 | D58: 否 | E58: =VLOOKUP(C58,H:I,2,0) -> 1 | F58: NEW-D2-公用事业-碳排放-北京环境交易所-人工 | G58: =VLOOKUP(F58,B:E,4,0) -> 1
A59: 1-行业经济 | B59: NEW-D2-公用事业-碳排放-北京环境交易所-人工 | C59: 日 | D59: 是 | E59: 1 | F59: NEW-D2-公用事业-碳排放-北京环境交易所-自动化 | G59: =VLOOKUP(F59,B:E,4,0) -> 1
A60: 1-行业经济 | B60: NEW-D2-公用事业-碳排放-北京环境交易所-自动化 | C60: 日 | D60: 是 | E60: 1 | F60: NEW-D2-公用事业-碳排放-四川联合环境交易所-人工 | G60: =VLOOKUP(F60,B:E,4,0) -> 1
A61: 1-行业经济 | B61: NEW-D2-公用事业-碳排放-四川联合环境交易所-人工 | C61: 日 | D61: 是 | E61: 1 | F61: NEW-D2-公用事业-碳排放-天津排放权交易所-人工 | G61: =VLOOKUP(F61,B:E,4,0) -> 1
A62: 1-行业经济 | B62: NEW-D2-公用事业-碳排放-天津排放权交易所-人工 | C62: 日 | D62: 是 | E62: 1 | F62: NEW-D2-公用事业-碳排放-天津排放权交易所-自动化 | G62: =VLOOKUP(F62,B:E,4,0) -> 1
A63: 1-行业经济 | B63: NEW-D2-公用事业-碳排放-天津排放权交易所-自动化 | C63: 日 | D63: 是 | E63: 1 | F63: NEW-D2-公用事业-碳排放-广州碳排放权交易所-人工 | G63: =VLOOKUP(F63,B:E,4,0) -> 1
A64: 1-行业经济 | B64: NEW-D2-公用事业-碳排放-广州碳排放权交易所-人工 | C64: 日 | D64: 是 | E64: 1 | F64: NEW-D2-公用事业-碳排放-广州碳排放权交易所-自动化 | G64: =VLOOKUP(F64,B:E,4,0) -> 1
A65: 1-行业经济 | B65: NEW-D2-公用事业-碳排放-广州碳排放权交易所-自动化 | C65: 日 | D65: 是 | E65: 1 | F65: NEW-D2-公用事业-碳排放-海峡股权交易中心-人工 | G65: =VLOOKUP(F65,B:E,4,0) -> 1
A66: 1-行业经济 | B66: NEW-D2-公用事业-碳排放-海峡股权交易中心-人工 | C66: 日 | D66: 是 | E66: 1 | F66: NEW-D2-公用事业-碳排放-海峡股权交易中心-自动化 | G66: =VLOOKUP(F66,B:E,4,0) -> 1
A67: 1-行业经济 | B67: NEW-D2-公用事业-碳排放-海峡股权交易中心-自动化 | C67: 日 | D67: 是 | E67: 1 | F67: NEW-D2-公用事业-碳排放-深圳排放权交易所-人工 | G67: =VLOOKUP(F67,B:E,4,0) -> 1
A68: 1-行业经济 | B68: NEW-D2-公用事业-碳排放-深圳排放权交易所-人工 | C68: 日 | D68: 是 | E68: 1 | F68: NEW-D2-公用事业-碳排放-深圳排放权交易所-自动化 | G68: =VLOOKUP(F68,B:E,4,0) -> 1
A69: 1-行业经济 | B69: NEW-D2-公用事业-碳排放-深圳排放权交易所-自动化 | C69: 日 | D69: 是 | E69: 1 | F69: NEW-D2-公用事业-碳排放-湖北碳排放权交易中心-人工 | G69: =VLOOKUP(F69,B:E,4,0) -> 1
A70: 1-行业经济 | B70: NEW-D2-公用事业-碳排放-湖北碳排放权交易中心-人工 | C70: 日 | D70: 是 | E70: 1 | F70: NEW-D2-公用事业-碳排放-湖北碳排放权交易中心-自动化 | G70: =VLOOKUP(F70,B:E,4,0) -> 1
A71: 1-行业经济 | B71: NEW-D2-公用事业-碳排放-湖北碳排放权交易中心-自动化 | C71: 日 | D71: 是 | E71: 1 | F71: NEW-D2-公用事业-碳排放-重庆-CCER-自动化 | G71: =VLOOKUP(F71,B:E,4,0) -> 1
A72: 1-行业经济 | B72: NEW-D2-公用事业-碳排放-重庆-CCER-自动化 | C72: 日 | D72: 否 | E72: =VLOOKUP(C72,H:I,2,0) -> 1 | F72: NEW-D2-公用事业-碳排放-重庆碳排放权交易中心-人工 | G72: =VLOOKUP(F72,B:E,4,0) -> 1
A73: 1-行业经济 | B73: NEW-D2-公用事业-碳排放-重庆碳排放权交易中心-人工 | C73: 日 | D73: 是 | E73: 1 | F73: NEW-D2-公用事业-碳排放-重庆碳排放权交易中心-自动化 | G73: =VLOOKUP(F73,B:E,4,0) -> 1
A74: 1-行业经济 | B74: NEW-D2-公用事业-碳排放-重庆碳排放权交易中心-自动化 | C74: 日 | D74: 是 | E74: 1 | F74: NEW-D3-公用事业-电力-出库（值班）-人工 | G74: =VLOOKUP(F74,B:E,4,0) -> 1
A75: 1-行业经济 | B75: NEW-D3-公用事业-电力-出库（值班）-人工 | C75: 日 | D75: 否 | E75: =VLOOKUP(C75,H:I,2,0) -> 1 | F75: NEW-D3-公用事业-电力-水库（值班）-人工 | G75: =VLOOKUP(F75,B:E,4,0) -> 1
A76: 1-行业经济 | B76: NEW-D3-公用事业-电力-水库（值班）-人工 | C76: 日 | D76: 否 | E76: =VLOOKUP(C76,H:I,2,0) -> 1 | F76: NEW-D4-公用事业-绿电-分地区累计-人工 | G76: =VLOOKUP(F76,B:E,4,0) -> 1
A77: 1-行业经济 | B77: NEW-D4-公用事业-绿电-分地区累计-人工 | C77: 日 | D77: 是 | E77: 1 | F77: NEW-D4-公用事业-绿电-认购总数-人工 | G77: =VLOOKUP(F77,B:E,4,0) -> 1
A78: 1-行业经济 | B78: NEW-D4-公用事业-绿电-认购总数-人工 | C78: 日 | D78: 是 | E78: 1 | F78: NEW-D4-公用事业-绿电-认购总数-自动化 | G78: =VLOOKUP(F78,B:E,4,0) -> 1
A79: 1-行业经济 | B79: NEW-D4-公用事业-绿电-认购总数-自动化 | C79: 日 | D79: 是 | E79: 1 | F79: NEW-D5-公用事业-新加坡交易所-北欧电力-自动化 | G79: =VLOOKUP(F79,B:E,4,0) -> 1
A80: 1-行业经济 | B80: NEW-D5-公用事业-新加坡交易所-北欧电力-自动化 | C80: 日 | D80: 否 | E80: =VLOOKUP(C80,H:I,2,0) -> 1 | F80: NEW-D1-农林牧渔-NYBOT农产品连续合约期货价-人工 | G80: =VLOOKUP(F80,B:E,4,0) -> 1
A81: 1-行业经济 | B81: NEW-D1-农林牧渔-NYBOT农产品连续合约期货价-人工 | C81: 日 | D81: 是 | E81: 1 | F81: NEW-D1-农林牧渔-国际期现货-人工 | G81: =VLOOKUP(F81,B:E,4,0) -> 1
A82: 1-行业经济 | B82: NEW-D1-农林牧渔-国际期现货-人工 | C82: 日 | D82: 是 | E82: 1 | F82: NEW-D1-农林牧渔-寿光1-人工 | G82: =VLOOKUP(F82,B:E,4,0) -> 1
A83: 1-行业经济 | B83: NEW-D1-农林牧渔-寿光1-人工 | C83: 日 | D83: 是 | E83: 1 | F83: NEW-D1-农林牧渔-寿光2-人工 | G83: =VLOOKUP(F83,B:E,4,0) -> 1
A84: 1-行业经济 | B84: NEW-D1-农林牧渔-寿光2-人工 | C84: 日 | D84: 否 | E84: =VLOOKUP(C84,H:I,2,0) -> 1 | F84: NEW-D1-农林牧渔-寿光3-人工 | G84: =VLOOKUP(F84,B:E,4,0) -> 1
A85: 1-行业经济 | B85: NEW-D1-农林牧渔-寿光3-人工 | C85: 日 | D85: 是 | E85: 1 | F85: NEW-D1-农林牧渔-寿光9-1-人工 | G85: =VLOOKUP(F85,B:E,4,0) -> 1
A86: 1-行业经济 | B86: NEW-D1-农林牧渔-寿光9-1-人工 | C86: 日 | D86: 是 | E86: 1 | F86: NEW-D1-农林牧渔-广西糖网-人工 | G86: =VLOOKUP(F86,B:E,4,0) -> 1
A87: 1-行业经济 | B87: NEW-D1-农林牧渔-广西糖网-人工 | C87: 日 | D87: 是 | E87: 1 | F87: NEW-D1-农林牧渔-棉籽价格-自动化 | G87: =VLOOKUP(F87,B:E,4,0) -> 1
A88: 1-行业经济 | B88: NEW-D1-农林牧渔-棉籽价格-自动化 | C88: 日 | D88: 是 | E88: 1 | F88: NEW-D1-农林牧渔-棉花5-3-自动化 | G88: =VLOOKUP(F88,B:E,4,0) -> 1
A89: 1-行业经济 | B89: NEW-D1-农林牧渔-棉花5-3-自动化 | C89: 日 | D89: 是 | E89: 1 | F89: NEW-D1-农林牧渔-棉花到厂价-自动化 | G89: =VLOOKUP(F89,B:E,4,0) -> 1
A90: 1-行业经济 | B90: NEW-D1-农林牧渔-棉花到厂价-自动化 | C90: 日 | D90: 是 | E90: 1 | F90: NEW-D1-农林牧渔-棉花到港价-人工 | G90: =VLOOKUP(F90,B:E,4,0) -> 1
A91: 1-行业经济 | B91: NEW-D1-农林牧渔-棉花到港价-人工 | C91: 日 | D91: 是 | E91: 1 | F91: NEW-D1-农林牧渔-棉花收购价-人工 | G91: =VLOOKUP(F91,B:E,4,0) -> 1
A92: 1-行业经济 | B92: NEW-D1-农林牧渔-棉花收购价-人工 | C92: 日 | D92: 是 | E92: 1 | F92: NEW-D1-农林牧渔-棉花美国现货-人工 | G92: =VLOOKUP(F92,B:E,4,0) -> 1
A93: 1-行业经济 | B93: NEW-D1-农林牧渔-棉花美国现货-人工 | C93: 日 | D93: 否 | E93: =VLOOKUP(C93,H:I,2,0) -> 1 | F93: NEW-D1-农林牧渔-江苏常州市场-自动化 | G93: =VLOOKUP(F93,B:E,4,0) -> 1
A94: 1-行业经济 | B94: NEW-D1-农林牧渔-江苏常州市场-自动化 | C94: 日 | D94: 是 | E94: 1 | F94: NEW-D1-农林牧渔-纱线价格指数-自动化 | G94: =VLOOKUP(F94,B:E,4,0) -> 1
A95: 1-行业经济 | B95: NEW-D1-农林牧渔-纱线价格指数-自动化 | C95: 日 | D95: 否 | E95: =VLOOKUP(C95,H:I,2,0) -> 1 | F95: NEW-D1-农林牧渔-维生素价格-自动化 | G95: =VLOOKUP(F95,B:E,4,0) -> 1
A96: 1-行业经济 | B96: NEW-D1-农林牧渔-维生素价格-自动化 | C96: 日 | D96: 是 | E96: 1 | F96: NEW-D1-农林牧渔-芝加哥期货-人工 | G96: =VLOOKUP(F96,B:E,4,0) -> 1
A97: 1-行业经济 | B97: NEW-D1-农林牧渔-芝加哥期货-人工 | C97: 日 | D97: 是 | E97: 1 | F97: NEW-D1-农林牧渔-钱清轻纺市场-人工 | G97: =VLOOKUP(F97,B:E,4,0) -> 1
A98: 1-行业经济 | B98: NEW-D1-农林牧渔-钱清轻纺市场-人工 | C98: 日 | D98: 是 | E98: 1 | F98: NEW-D10-农林牧渔-日同比价格指数-自动化 | G98: =VLOOKUP(F98,B:E,4,0) -> 1
A99: 1-行业经济 | B99: NEW-D10-农林牧渔-日同比价格指数-自动化 | C99: 日 | D99: 否 | E99: =VLOOKUP(C99,H:I,2,0) -> 1 | F99: NEW-D10-农林牧渔-日定基价格指数-自动化 | G99: =VLOOKUP(F99,B:E,4,0) -> 1
A100: 1-行业经济 | B100: NEW-D10-农林牧渔-日定基价格指数-自动化 | C100: 日 | D100: 是 | E100: 1 | F100: NEW-D10-农林牧渔-日环比价格指数-自动化 | G100: =VLOOKUP(F100,B:E,4,0) -> 1
...

Sheet Sheet1
B3: 模版频率
B4: 日 | C4: 半年 | D4: 不定期 | E4: 季 | F4: 年 | G4: 旬 | H4: 月 | I4: 周 | J4: (Blank) | K4: Grand Total
A5: 计数项:模版名称 | B5: 1927 | C5: 12 | D5: 16 | E5: 335 | F5: 2038 | G5: 17 | H5: 2982 | I5: 1138 | J5: 2333 | K5: 10798

Sheet Sheet2
C6: 频率 | D6: 任务数 | E6: 根据时效每月处理任务数 | F6: 每月人/日（按照每个任务平均1分钟计算） | G6: 加了冷静期，粗略估计
C7: 日 | D7: 1927 | E7: =D7*24 -> 46248 | F7: =E7/480 -> 96.35
C8: 半年 | D8: 12
C9: 不定期 | D9: 16
C10: 季 | D10: 335 | E10: =D10*10 -> 3350 | F10: =E10/480 -> 6.9791667
C11: 年 | D11: 2038 | E11: =D11*6 -> 12228 | F11: =E11/480 -> 25.475
C12: 旬 | D12: 17
C13: 月 | D13: 2982 | E13: =D13*10 -> 29820 | F13: =E13/480 -> 62.125 | G13: 31
C14: 周 | D14: 1138 | E14: =D14*24 -> 27312 | F14: =E14/480 -> 56.9
C15: (空白) | D15: 2333
C16: 总计 | D16: 10798 | E16: =SUM(E7:E14) -> 118958 | F16: =E16/480 -> 247.82917

Sheet Sheet3
A1: 模版名称 | F1: 核心重点指标
A2: NEW-DWMY-交运-中航信-当日预定指数-日 | F2: NEW-M1-化工-OPEC-VLCC运价指数
A3: NEW-DWMY-交运-中航信-需求指数 | F3: 国际宏观-M2-美国-劳工部-非农每周工作时间TableB-2
A4: NEW-HW1-化工-库存模板-丙酮江阴库存 | F4: NEW-M6-公用事业-杭州
A5: NEW-HW1-化工-库存模板-华东主港乙二醇库存及主流库区统计分析 | F5: NEW-M3-农林牧渔-USDA豆油供需平衡表
A6: NEW-HW1-化工-库存模板-华东乙二醇码头库存 | F6: NEW-Y1-交运-轨道交通协会-地铁
A7: NEW-HW1-化工-库存模板-苯酚江阴港口库存 | F7: 【经营数据】-汽车-M1-亚星客车
A8: NEW-D1-TMT-每日票房 | F8: 新宏观-M4-国统局-36个城市CPI分项-36个城市CPI分项
A9: NEW-D1-TMT-每日票房 | F9: 地方经济三期-Y35-云南省统计公报-普洱市
A10: NEW-D1-交运-BDI | F10: NEW-D4-化工-隆众化肥及其他-磷酸出厂价
A11: NEW-D1-交运-FDI | F11: NEW-M15-化工-隆众月报-4
A12: NEW-D1-交运-中国水运网运价 | F12: 新宏观-M3-海关总署-全国出口商品贸易同比指数(HS4分类)
... A5498: 地方经济运行-M1-新疆(非重点)-新疆 | F5498: 【经营数据】-食品饮料-Q1-海天味业
A5499: 地方经济运行-M1-新疆(非重点)-昌吉回族
A5500: 地方经济运行-M1-新疆(非重点)-昌吉回族区县
A5501: 地方经济运行-M1-新疆(非重点)-石河子
A5502: 地方经济运行-M1-新疆(非重点)-阿克苏
A5503: 地方经济运行-M1-新疆(非重点)-阿克苏区县
A5504: 地方经济运行-M1-新疆(非重点)-阿勒泰区县
A5505: 地方经济运行-M1-新疆(非重点)-阿拉尔市
A5506: 地方经济运行-M1-无锡市-宜兴市
A5507: 地方经济运行-M1-无锡市-惠山区
A5508: 地方经济运行-M1-无锡市-无锡
A5509: 地方经济运行-M1-无锡市-无锡市专利交通邮政
A5510: 地方经济运行-M1-无锡市-无锡市其他
... A10799: 衍生指标-NEW-海关新增指标模板
